mell/__init__.py
mell/consts.py
mell/main.py
mell-2.0.7.dist-info/METADATA
mell-2.0.7.dist-info/WHEEL
mell-2.0.7.dist-info/entry_points.txt
mell-2.0.7.dist-info/top_level.txt
mell-2.0.7.dist-info/RECORD
