Metadata-Version: 2.1
Name: mell
Version: 2.0.7
Summary: Generate anything from template files and metadata files!
Home-page: https://github.com/diegofps/mell
Author: Diego Souza
Author-email: diegofpsouza+mell@gmail.com
Classifier: Programming Language :: Python :: 3
Classifier: License :: OSI Approved :: MIT License
Classifier: Operating System :: OS Independent
Requires-Dist: jinja2
Provides-Extra: full
